nanodpo/causal_transformer.py
nanodpo/dpo_onemodel_trainer.py
nanodpo/multiclass_trainer.py
nanodpo/preference_data.py
nanodpo/sequence_data.py
nanodpo/simple_sequence_model.py
nanodpo/sinusoidal_positional_encoding.py
nanodpo-0.1.post1.dist-info/LICENSE
nanodpo-0.1.post1.dist-info/METADATA
nanodpo-0.1.post1.dist-info/WHEEL
nanodpo-0.1.post1.dist-info/RECORD
