Metadata-Version: 2.1
Name: nanoDPO
Version: 0.1.post1
Summary: A nimble and innovative implementation of the Direct Preference Optimization (DPO) algorithm with Causal Transformer and LSTM model for time series data, inspired by the paper of DPO in fine-tuning unsupervised Language Models
License: Apache-2.0
Author: James Liu
Classifier: License :: OSI Approved :: Apache Software License
Classifier: Programming Language :: Python :: 2
Classifier: Programming Language :: Python :: 2.7
Classifier: Programming Language :: Python :: 3
Classifier: Programming Language :: Python :: 3.4
Classifier: Programming Language :: Python :: 3.5
Classifier: Programming Language :: Python :: 3.6
Classifier: Programming Language :: Python :: 3.7
Classifier: Programming Language :: Python :: 3.8
Classifier: Programming Language :: Python :: 3.9
Classifier: Programming Language :: Python :: 3.10
Classifier: Programming Language :: Python :: 3.11
Provides-Extra: test
